{
  "string": [
    {
      "name": "module_desc",
      "value": "module description"
    },
    {
      "name": "EntryAbility_desc",
      "value": "description"
    },
    {
      "name": "EntryAbility_label",
      "value": "label"
    },
    {
      "name": "mic_permission_reason",
      "value": "Recording bird sounds requires microphone access."
    },
    {
      "name": "internet_permission_reason",
      "value": "Uploading audio and identifying birds requires network access."
    },
    {
      "name": "location_permission_reason",
      "value": "Saving bird recognition locations requires location access."
    }
  ]
}
